cardiac_geometries/__init__.py
cardiac_geometries/__main__.py
cardiac_geometries/_import_checks.py
cardiac_geometries/_mesh.py
cardiac_geometries/aha.py
cardiac_geometries/bai_atlas.py
cardiac_geometries/calculus.py
cardiac_geometries/cli.py
cardiac_geometries/dolfin_utils.py
cardiac_geometries/geometry.py
cardiac_geometries/utils.py
cardiac_geometries/viz.py
cardiac_geometries/fibers/__init__.py
cardiac_geometries/fibers/_biv_ellipsoid.py
cardiac_geometries/fibers/_lv_ellipsoid.py
cardiac_geometries/fibers/_slab.py
cardiac_geometries/fibers/_utils.py
cardiac_geometries-1.1.8.dist-info/licenses/LICENSE
cardiac_geometries-1.1.8.dist-info/METADATA
cardiac_geometries-1.1.8.dist-info/WHEEL
cardiac_geometries-1.1.8.dist-info/entry_points.txt
cardiac_geometries-1.1.8.dist-info/top_level.txt
cardiac_geometries-1.1.8.dist-info/RECORD
