Metadata-Version: 2.4
Name: cardiac_geometries
Version: 1.1.8
Summary: A python library for cardiac geometries
Author-email: Henrik Finsberg <henriknf@simula.no>
License: MIT
Project-URL: Homepage, https://github.com/ComputationalPhysiology/cardiac-geometries
Keywords: cardiac,geometry,mesh,gmsh
Classifier: License :: OSI Approved :: MIT License
Classifier: Programming Language :: Python :: 3
Classifier: Programming Language :: Python :: 3 :: Only
Requires-Python: >=3.6
License-File: LICENSE
Requires-Dist: cardiac-geometries-core<1.0.0,>=0.2.1
Requires-Dist: meshio2
Requires-Dist: numpy
Requires-Dist: rich-click
Provides-Extra: dev
Requires-Dist: bump2version; extra == "dev"
Requires-Dist: ipython; extra == "dev"
Requires-Dist: pdbpp; extra == "dev"
Requires-Dist: pre-commit; extra == "dev"
Provides-Extra: docs
Requires-Dist: jupyter-book<2.0; extra == "docs"
Requires-Dist: jupytext; extra == "docs"
Requires-Dist: sphinxcontrib-bibtex; extra == "docs"
Provides-Extra: gmsh
Requires-Dist: gmsh; extra == "gmsh"
Provides-Extra: ldrb
Requires-Dist: ldrb; extra == "ldrb"
Provides-Extra: pypi
Requires-Dist: build; extra == "pypi"
Provides-Extra: test
Requires-Dist: ldrb; extra == "test"
Requires-Dist: pytest; extra == "test"
Requires-Dist: pytest-cov; extra == "test"
Provides-Extra: viz
Requires-Dist: h5py; extra == "viz"
Dynamic: license-file
